README.md
setup.py
getUniprot/__init__.py
getUniprot/uniprot.py
get_uniprot.egg-info/PKG-INFO
get_uniprot.egg-info/SOURCES.txt
get_uniprot.egg-info/dependency_links.txt
get_uniprot.egg-info/entry_points.txt
get_uniprot.egg-info/requires.txt
get_uniprot.egg-info/top_level.txt