Metadata-Version: 1.0
Name: get-uniprot
Version: 1.0
Summary: Python CLI for accessing protein .fasta sequences using the UNIPROT API.
Home-page: https://github.com/J-E-J-S/get-uniprot
Author: James Sanders
Author-email: james.sanders1711@gmail.com
License: UNKNOWN
Platform: UNKNOWN
